ai_code_review/__init__.py
ai_code_review/cli.py
odin_code_review_github_ai_partner-0.1.0.dist-info/licenses/LICENSE
odin_code_review_github_ai_partner-0.1.0.dist-info/METADATA
odin_code_review_github_ai_partner-0.1.0.dist-info/WHEEL
odin_code_review_github_ai_partner-0.1.0.dist-info/entry_points.txt
odin_code_review_github_ai_partner-0.1.0.dist-info/top_level.txt
odin_code_review_github_ai_partner-0.1.0.dist-info/RECORD
