Metadata-Version: 2.4
Name: Odin-code-review-github-ai-partner
Version: 0.1.0
Summary: Automated AI-powered GitHub Pull Request code review
Home-page: https://github.com/Yassinelaadraoui/AI-Code-Review-Script
Author: Yassine Laadraoui
License: MIT
Requires-Python: >=3.8
License-File: LICENSE
Requires-Dist: PyGithub>=1.77
Requires-Dist: requests>=2.31
Dynamic: author
Dynamic: description
Dynamic: description-content-type
Dynamic: home-page
Dynamic: license
Dynamic: license-file
Dynamic: requires-dist
Dynamic: requires-python
Dynamic: summary
